pori_python/__init__.py
pori_python/py.typed
pori_python/types.py
pori_python/graphkb/__init__.py
pori_python/graphkb/constants.py
pori_python/graphkb/genes.py
pori_python/graphkb/match.py
pori_python/graphkb/statement.py
pori_python/graphkb/util.py
pori_python/graphkb/vocab.py
pori_python/ipr/__init__.py
pori_python/ipr/annotate.py
pori_python/ipr/connection.py
pori_python/ipr/constants.py
pori_python/ipr/content.spec.json
pori_python/ipr/inputs.py
pori_python/ipr/ipr.py
pori_python/ipr/main.py
pori_python/ipr/summary.py
pori_python/ipr/therapeutic_options.py
pori_python/ipr/util.py
pori_python-1.2.0.dist-info/licenses/LICENSE
tests/__init__.py
tests/test_graphkb/__init__.py
tests/test_graphkb/data.py
tests/test_graphkb/test_genes.py
tests/test_graphkb/test_graphkb.py
tests/test_graphkb/test_match.py
tests/test_graphkb/test_statement.py
tests/test_graphkb/test_util.py
tests/test_graphkb/test_vocab.py
tests/test_ipr/__init__.py
tests/test_ipr/constants.py
tests/test_ipr/test_annotate.py
tests/test_ipr/test_connection.py
tests/test_ipr/test_inputs.py
tests/test_ipr/test_ipr.py
tests/test_ipr/test_main.py
tests/test_ipr/test_probe.py
tests/test_ipr/test_summary.py
tests/test_ipr/test_upload.py
tests/test_ipr/test_util.py
tests/test_ipr/util.py
pori_python-1.2.0.dist-info/METADATA
pori_python-1.2.0.dist-info/WHEEL
pori_python-1.2.0.dist-info/dependency_links.txt
pori_python-1.2.0.dist-info/entry_points.txt
pori_python-1.2.0.dist-info/top_level.txt
pori_python-1.2.0.dist-info/RECORD
