Metadata-Version: 2.4
Name: pori_python
Version: 1.2.0
Home-page: https://github.com/bcgsc/pori_python
Author-email: dat@bcgsc.ca
Maintainer-email: dat@bcgsc.ca
Requires-Python: >=3.9
License-File: LICENSE
Requires-Dist: biopython
Requires-Dist: jsonschema
Requires-Dist: pandas>=1.1.0
Requires-Dist: requests
Requires-Dist: tqdm
Requires-Dist: typing_extensions<5,>=3.7.4.2
Provides-Extra: deploy
Requires-Dist: twine; extra == "deploy"
Requires-Dist: wheel; extra == "deploy"
Requires-Dist: m2r; extra == "deploy"
Provides-Extra: test
Requires-Dist: pytest; extra == "test"
Requires-Dist: pytest-cov; extra == "test"
Requires-Dist: pytest-runner; extra == "test"
Provides-Extra: docs
Requires-Dist: mkdocs; extra == "docs"
Requires-Dist: mkdocs-material; extra == "docs"
Requires-Dist: markdown-refdocs; extra == "docs"
Requires-Dist: mkdocs-redirects; extra == "docs"
Provides-Extra: dev
Requires-Dist: twine; extra == "dev"
Requires-Dist: wheel; extra == "dev"
Requires-Dist: m2r; extra == "dev"
Requires-Dist: pytest; extra == "dev"
Requires-Dist: pytest-runner; extra == "dev"
Requires-Dist: pytest-cov; extra == "dev"
Requires-Dist: mkdocs; extra == "dev"
Requires-Dist: mkdocs-material; extra == "dev"
Requires-Dist: mkdocs-redirects; extra == "dev"
Requires-Dist: markdown-refdocs; extra == "dev"
Requires-Dist: flake8; extra == "dev"
Requires-Dist: black; extra == "dev"
Requires-Dist: flake8-annotations; extra == "dev"
Requires-Dist: isort; extra == "dev"
Requires-Dist: mypy; extra == "dev"
Dynamic: license-file
